<annotation>
	<folder></folder>
	<filename>__EX_954139138_420197-1_jpg.rf.27e028062a91806247f466d0fbb0189e.jpg</filename>
	<path>__EX_954139138_420197-1_jpg.rf.27e028062a91806247f466d0fbb0189e.jpg</path>
	<source>
		<database>roboflow.ai</database>
	</source>
	<size>
		<width>640</width>
		<height>640</height>
		<depth>3</depth>
	</size>
	<segmented>0</segmented>
	<object>
		<name>Mary</name>
		<pose>Unspecified</pose>
		<truncated>0</truncated>
		<difficult>0</difficult>
		<occluded>0</occluded>
		<bndbox>
			<xmin>30</xmin>
			<xmax>615</xmax>
			<ymin>82</ymin>
			<ymax>641</ymax>
		</bndbox>
	</object>
</annotation>
