<annotation>
	<folder></folder>
	<filename>__EX_1150514595_497952270-1_jpg.rf.8bc30303a84787d93ac7c45fa4c3fc33.jpg</filename>
	<path>__EX_1150514595_497952270-1_jpg.rf.8bc30303a84787d93ac7c45fa4c3fc33.jpg</path>
	<source>
		<database>roboflow.ai</database>
	</source>
	<size>
		<width>640</width>
		<height>640</height>
		<depth>3</depth>
	</size>
	<segmented>0</segmented>
	<object>
		<name>Mary</name>
		<pose>Unspecified</pose>
		<truncated>0</truncated>
		<difficult>0</difficult>
		<occluded>0</occluded>
		<bndbox>
			<xmin>1</xmin>
			<xmax>418</xmax>
			<ymin>75</ymin>
			<ymax>575</ymax>
		</bndbox>
	</object>
	<object>
		<name>Holo</name>
		<pose>Unspecified</pose>
		<truncated>0</truncated>
		<difficult>0</difficult>
		<occluded>0</occluded>
		<bndbox>
			<xmin>127</xmin>
			<xmax>286</xmax>
			<ymin>50</ymin>
			<ymax>106</ymax>
		</bndbox>
	</object>
	<object>
		<name>Holo</name>
		<pose>Unspecified</pose>
		<truncated>0</truncated>
		<difficult>0</difficult>
		<occluded>0</occluded>
		<bndbox>
			<xmin>452</xmin>
			<xmax>609</xmax>
			<ymin>60</ymin>
			<ymax>137</ymax>
		</bndbox>
	</object>
</annotation>
