<annotation>
	<folder></folder>
	<filename>__EX_575004734_1179914329-1_jpg.rf.6801fe60c0f87c655f04979a38865d00.jpg</filename>
	<path>__EX_575004734_1179914329-1_jpg.rf.6801fe60c0f87c655f04979a38865d00.jpg</path>
	<source>
		<database>roboflow.ai</database>
	</source>
	<size>
		<width>640</width>
		<height>640</height>
		<depth>3</depth>
	</size>
	<segmented>0</segmented>
	<object>
		<name>Mary</name>
		<pose>Unspecified</pose>
		<truncated>0</truncated>
		<difficult>0</difficult>
		<occluded>0</occluded>
		<bndbox>
			<xmin>69</xmin>
			<xmax>555</xmax>
			<ymin>41</ymin>
			<ymax>519</ymax>
		</bndbox>
	</object>
	<object>
		<name>Holo</name>
		<pose>Unspecified</pose>
		<truncated>0</truncated>
		<difficult>0</difficult>
		<occluded>0</occluded>
		<bndbox>
			<xmin>213</xmin>
			<xmax>401</xmax>
			<ymin>29</ymin>
			<ymax>93</ymax>
		</bndbox>
	</object>
</annotation>
